mkdocs_chatbot/__init__.py
mkdocs_chatbot/plugin.py
mkdocs_chatbot/assets/extra.css
mkdocs_chatbot/overrides/main.html
mkdocs_chatbot-0.0.2.dist-info/METADATA
mkdocs_chatbot-0.0.2.dist-info/WHEEL
mkdocs_chatbot-0.0.2.dist-info/entry_points.txt
mkdocs_chatbot-0.0.2.dist-info/licenses/LICENSE
mkdocs_chatbot-0.0.2.dist-info/RECORD
