Metadata-Version: 2.4
Name: mkdocs-chatbot
Version: 0.0.2
Summary: A MKDocs plugin that adds an AI-powered chatbot to your documentation.
Project-URL: Repository, https://github.com/jonco5555/mkdocs-chatbot
Project-URL: Documentation, https://jonco5555.github.io/mkdocs-chatbot/
Author-email: Yonatan Cohen <jonco5555@gmail.com>
License-File: LICENSE
Requires-Python: >=3.8
Requires-Dist: mkdocs>=1.6.1
